{"organizations": [], "uuid": "a48a778ec3dcbf44bd6910bfca25d05839c31f00", "thread": {"social": {"gplus": {"shares": 0}, "pinterest": {"shares": 0}, "vk": {"shares": 0}, "linkedin": {"shares": 0}, "facebook": {"likes": 0, "shares": 0, "comments": 0}, "stumbledupon": {"shares": 0}}, "site_full": "www.cnbc.com", "main_image": "https://fm.cnbc.com/applications/cnbc.com/resources/img/editorial/2017/12/18/104905553-GettyImages-894912586.1910x1000.jpg", "site_section": "", "section_title": "", "url": "https://www.cnbc.com/2018/01/08/trump-close-to-decision-on-fed-vice-chair-pick-administration-official-says.html", "country": "US", "domain_rank": 767, "title": "Trump close to decision on Fed vice chair pick, administration official says", "performance_score": 0, "site": "cnbc.com", "participants_count": 0, "title_full": "", "spam_score": 0.023, "site_type": "news", "published": "2018-01-08T23:13:00.000+02:00", "replies_count": 0, "uuid": "a48a778ec3dcbf44bd6910bfca25d05839c31f00"}, "author": "Saul Loeb", "url": "https://www.cnbc.com/2018/01/08/trump-close-to-decision-on-fed-vice-chair-pick-administration-official-says.html", "ord_in_thread": 0, "title": "Trump close to decision on Fed vice chair pick, administration official says", "locations": [], "entities": {"persons": [{"name": "momen", "sentiment": "negative"}, {"name": "trump", "sentiment": "negative"}, {"name": "stanley fischer", "sentiment": "none"}, {"name": "donald trump", "sentiment": "none"}, {"name": "saul loeb", "sentiment": "none"}], "locations": [{"name": "washington, dc", "sentiment": "none"}], "organizations": [{"name": "fed", "sentiment": "negative"}, {"name": "ronald reagan building and international trade center", "sentiment": "none"}, {"name": "federal reserve", "sentiment": "none"}]}, "highlightText": "", "language": "english", "persons": [], "text": "President Donald Trump is close to making a decision on who to nominate as vice chair of the Federal Reserve, an administration official said on Monday.\nThe position became vacant in October after veteran central banker Stanley Fischer stepped down for personal reasons.", "external_links": [], "published": "2018-01-08T23:13:00.000+02:00", "crawled": "2018-01-08T23:13:58.011+02:00", "highlightTitle": ""}