{"organizations": [], "uuid": "109fe69336e39c7d081918e47a06319f163f65ef", "thread": {"social": {"gplus": {"shares": 0}, "pinterest": {"shares": 0}, "vk": {"shares": 0}, "linkedin": {"shares": 0}, "facebook": {"likes": 0, "shares": 0, "comments": 0}, "stumbledupon": {"shares": 0}}, "site_full": "www.cnbc.com", "main_image": "", "site_section": "http://www.cnbc.com/id/10000027/page/2", "section_title": "Press Releases - CNBC", "url": "http://www.cnbc.com/2018/01/23/business-wire-american-campus-communities-announces-quarterly-dividend.html", "country": "US", "domain_rank": 767, "title": "American Campus Communities Announces Quarterly Dividend", "performance_score": 0, "site": "cnbc.com", "participants_count": 1, "title_full": "", "spam_score": 0.035, "site_type": "news", "published": "2018-01-24T01:00:00.000+02:00", "replies_count": 0, "uuid": "109fe69336e39c7d081918e47a06319f163f65ef"}, "author": "cnbc.com", "url": "http://www.cnbc.com/2018/01/23/business-wire-american-campus-communities-announces-quarterly-dividend.html", "ord_in_thread": 0, "title": "American Campus Communities Announces Quarterly Dividend", "locations": [], "entities": {"persons": [], "locations": [{"name": "austin", "sentiment": "none"}, {"name": "texas", "sentiment": "none"}, {"name": "u.s.", "sentiment": "none"}, {"name": "united states", "sentiment": "none"}], "organizations": [{"name": "nyse", "sentiment": "negative"}, {"name": "american campus communities, inc.", "sentiment": "neutral"}, {"name": "acc", "sentiment": "none"}, {"name": "american campus communities", "sentiment": "none"}, {"name": "american campus communities american campus communities, inc.", "sentiment": "none"}]}, "highlightText": "", "language": "english", "persons": [], "text": "AUSTIN, Texas--(BUSINESS WIRE)-- American Campus Communities, Inc. (NYSE: ACC), the nation’s largest owner and manager of high-quality student housing properties in the U.S., announced that on January 23, 2018 its Board of Directors declared a regular quarterly dividend of $0.44 per share of common stock, payable on February 16, 2018, to shareholders of record at the close of business on February 2, 2018.\nAbout American Campus Communities\nAmerican Campus Communities, Inc. is the largest owner, manager and developer of high-quality student housing communities in the United States. The company is a fully integrated, self-managed and self-administered equity real estate investment trust (REIT) with expertise in the design, finance, development, construction management and operational management of student housing properties. As of September 30, 2017, American Campus Communities owned 166 student housing properties containing approximately 102,500 beds. Including its owned and third-party managed properties, ACC's total managed portfolio consisted of 204 properties with approximately 131,300 beds. Visit www.americancampus.com .\nForward-Looking Statements\nIn addition to historical information, this press release contains under the applicable federal securities law. These statements are based on management’s current expectations and assumptions regarding markets in which American Campus Communities, Inc. (the “Company”) operates, operational strategies, anticipated events and trends, the economy, and other future conditions. Forward-looking statements are not guarantees of future performance and involve certain risks and uncertainties, which are difficult to predict. For discussions of some risks and uncertainties that could cause actual results to differ materially from those expressed or implied by the , please refer to our filings with the Securities and Exchange Commission, including our Annual Report on Form 10-K for the year ended December 31, 2016 under the heading “Risk Factors” and under the heading “Business - Forward-looking Statements” and subsequent quarterly reports on Form 10-Q. We undertake no obligation to publicly update any , including our expected 2017 operating results, whether as a result of new information, future events, or otherwise.\nView source version on businesswire.com : http://www.businesswire.com/news/home/20180123005427/en/\nAmerican Campus Communities, Inc.\nRyan Dennison, 512-732-1000\nInvestor Relations\nSource: American Campus Communities, Inc.", "external_links": ["http://cts.businesswire.com/ct/CT?id=smartlink&url=http%3A%2F%2Fwww.americancampus.com&esheet=51747249&newsitemid=20180123005427&lan=en-US&anchor=www.americancampus.com&index=1&md5=8336bc9c7efa9320ee2ef288dde45933", "http://www.businesswire.com/news/home/20180123005427/en/"], "published": "2018-01-24T01:00:00.000+02:00", "crawled": "2018-01-24T01:41:14.001+02:00", "highlightTitle": ""}