{"organizations": [], "uuid": "9f047d02246b092df27daa868deadec605428d23", "thread": {"social": {"gplus": {"shares": 0}, "pinterest": {"shares": 0}, "vk": {"shares": 0}, "linkedin": {"shares": 0}, "facebook": {"likes": 0, "shares": 0, "comments": 0}, "stumbledupon": {"shares": 0}}, "site_full": "www.reuters.com", "main_image": "https://s4.reutersmedia.net/resources_v2/images/rcom-default.png", "site_section": "http://feeds.reuters.com/reuters/companyNews\r", "section_title": "Reuters: Company News", "url": "https://www.reuters.com/article/britain-press-business/press-digest-british-business-jan-24-idUSL4N1PJ08F", "country": "US", "domain_rank": 408, "title": "PRESS DIGEST- British Business - Jan 24", "performance_score": 0, "site": "reuters.com", "participants_count": 0, "title_full": "", "spam_score": 0.0, "site_type": "news", "published": "2018-01-24T02:59:00.000+02:00", "replies_count": 0, "uuid": "9f047d02246b092df27daa868deadec605428d23"}, "author": "", "url": "https://www.reuters.com/article/britain-press-business/press-digest-british-business-jan-24-idUSL4N1PJ08F", "ord_in_thread": 0, "title": "PRESS DIGEST- British Business - Jan 24", "locations": [], "entities": {"persons": [{"name": "dominic chappell", "sentiment": "none"}], "locations": [{"name": "uk", "sentiment": "none"}], "organizations": [{"name": "reuters staff", "sentiment": "negative"}, {"name": "twenty-first century fox inc", "sentiment": "none"}, {"name": "times", "sentiment": "none"}, {"name": "nhs", "sentiment": "none"}, {"name": "palmer & ha", "sentiment": "none"}, {"name": "home office", "sentiment": "none"}, {"name": "reuters", "sentiment": "none"}, {"name": "sky plc", "sentiment": "none"}, {"name": "barclays plc", "sentiment": "none"}]}, "highlightText": "", "language": "english", "persons": [], "text": "Jan 24 (Reuters) - The following are the top stories on the business pages of British newspapers. Reuters has not verified these stories and does not vouch for their accuracy.\nThe Times\n- The independent accountant chosen by Barclays Plc to rule on its controversial ringfencing plan and the effect on 200,000 pension fund members previously had been in charge of the team advising the disgraced businessman Dominic Chappell on buying BHS for 1 pound ($1.40). bit.ly/2DFfu8A\n- The proposed takeover of Sky Plc by Twenty-First Century Fox Inc edged closer yesterday after a watchdog said that the deal raised concerns about media plurality but outlined how they could be assuaged. bit.ly/2GazCOh\nThe Guardian\n- Seniors doctors from overseas who have been appointed to fill key roles in hospitals around the UK are being blocked from taking up their jobs by the Home Office because their NHS salaries are too low under immigration rules. bit.ly/2n4FtM9\n- Groceries wholesaler Palmer & Harvey had debts of more than 700 million pounds when it collapsed in November, according to an administrators' report published on Tuesday. bit.ly/2DyIG1B\nThe Telegraph\n- Taxpayer-owned Royal Bank of Scotland Group Plc is ditching the London headquarters from which disgraced former boss Fred Goodwin ran his bloated banking empire prior to the financial crisis. bit.ly/2E3CTy7\n- Thousands of J Sainsbury Plc's shop staff have been put at risk following an overhaul of its store management roles in the latest cost-cutting drive by the company. bit.ly/2n5UQEm\nSky News\n- Tesco Plc has poached the boss of one of Ireland's biggest lenders to run its financial services arm, a move that will deal a blow to the state-backed Royal Bank of Scotland Group Plc. bit.ly/2n3kb2q\n- The manufacturer of Huggies nappies, Andrex toilet paper and Kleenex tissues, Kimberly-Clark Corp has refused to rule out job losses among its UK workforce as it seeks to cut up to 5,500 roles worldwide. bit.ly/2E27UT1\nThe Independent\n- The European Union has taken eight countries off its tax haven blacklist after they apparently took measures to \"remedy\" EU concerns about their approaches to tax dodging. ind.pn/2ryKK4c\n- Travellers to the Lake District and south-west Scotland will get a new option from the summer when Carlisle airport re-opens for scheduled passenger traffic. ind.pn/2n3z98O\n$1 = 0.7139 pounds Compiled by Bengaluru newsroom\n ", "external_links": [], "published": "2018-01-24T02:59:00.000+02:00", "crawled": "2018-01-24T03:27:19.002+02:00", "highlightTitle": ""}